mcblueprints/__init__.py
mcblueprints/__main__.py
mcblueprints/build/__init__.py
mcblueprints/build/blueprints_build_context.py
mcblueprints/cli/__init__.py
mcblueprints/cli/cli.py
mcblueprints/lib/__init__.py
mcblueprints/lib/resource/__init__.py
mcblueprints/lib/resource/blueprint/__init__.py
mcblueprints/lib/resource/blueprint/blueprint.py
mcblueprints/lib/resource/blueprint/blueprint_deserializer.py
mcblueprints/lib/resource/blueprint/blueprint_transformer.py
mcblueprints/lib/resource/blueprint/palette_entry/__init__.py
mcblueprints/lib/resource/blueprint/palette_entry/abc/__init__.py
mcblueprints/lib/resource/blueprint/palette_entry/abc/blueprint_palette_entry.py
mcblueprints/lib/resource/blueprint/palette_entry/block_blueprint_palette_entry.py
mcblueprints/lib/resource/blueprint/palette_entry/blueprint_blueprint_palette_entry.py
mcblueprints/lib/resource/blueprint/palette_entry/material_blueprint_palette_entry.py
mcblueprints/lib/resource/blueprint/palette_entry/void_blueprint_palette_entry.py
mcblueprints/lib/resource/blueprint/types.py
mcblueprints/lib/resource/blueprint/types.pyi
mcblueprints/lib/resource/filter/__init__.py
mcblueprints/lib/resource/filter/filter.py
mcblueprints/lib/resource/filter/filter_deserializer.py
mcblueprints/lib/resource/filter/rule/__init__.py
mcblueprints/lib/resource/filter/rule/abc/__init__.py
mcblueprints/lib/resource/filter/rule/abc/filter_rule.py
mcblueprints/lib/resource/filter/rule/keep_blocks_filter_rule.py
mcblueprints/lib/resource/filter/rule/keep_materials_filter_rule.py
mcblueprints/lib/resource/filter/rule/replace_blocks_filter_rule.py
mcblueprints/lib/resource/filter/rule/replace_materials_filter_rule.py
mcblueprints/lib/resource/filter/types.py
mcblueprints/lib/resource/filter/types.pyi
mcblueprints/lib/resource/material/__init__.py
mcblueprints/lib/resource/material/material.py
mcblueprints/lib/resource/material/material_deserializer.py
mcblueprints/lib/resource/material/types.py
mcblueprints-0.1.0.dist-info/LICENSE.txt
mcblueprints-0.1.0.dist-info/WHEEL
mcblueprints-0.1.0.dist-info/METADATA
mcblueprints-0.1.0.dist-info/RECORD
